[{"id": 7553576, "name": "ул. Алексея Дикого, д. 5, к. 1"}, {"id": 7553579, "name": "ул. Алексея Дикого, д. 5, к. 2"}, {"id": 7553583, "name": "ул. Алексея Дикого, д. 7, к. 1"}, {"id": 7553585, "name": "ул. Алексея Дикого, д. 7, к. 2"}, {"id": 7553586, "name": "ул. Алексея Дикого, д. 7, к. 3"}, {"id": 7553593, "name": "ул. Алексея Дикого, д. 16А"}, {"id": 7553600, "name": "ул. Алексея Дикого, д. 18"}, {"id": 7553672, "name": "ул. Алексея Дикого, д. 20"}, {"id": 7554330, "name": "ул. Братская, д. 15, к. 1"}, {"id": 7554333, "name": "ул. Братская, д. 15, к. 2"}, {"id": 7554337, "name": "ул. Братская, д. 15, к. 3"}, {"id": 7554342, "name": "ул. Братская, д. 17, к. 1"}, {"id": 7554346, "name": "ул. Братская, д. 17, к. 2"}, {"id": 7554581, "name": "ул. Братская, д. 19, к. 1"}, {"id": 7554586, "name": "ул. Братская, д. 19, к. 2"}, {"id": 7554594, "name": "ул. Братская, д. 19, к. 3"}, {"id": 7554598, "name": "ул. Братская, д. 21, к. 1"}, {"id": 7554608, "name": "ул. Братская, д. 21, к. 2"}, {"id": 9066801, "name": "ул. Братская, д. 23, к. 1"}, {"id": 7554613, "name": "ул. Братская, д. 23, к. 2"}, {"id": 7554617, "name": "ул. Братская, д. 23, к. 3"}, {"id": 7554623, "name": "ул. Братская, д. 25, к. 1"}, {"id": 7554627, "name": "ул. Братская, д. 25, к. 2"}, {"id": 7554629, "name": "ул. Братская, д. 27, к. 1"}, {"id": 7554632, "name": "ул. Братская, д. 27, к. 2"}, {"id": 7554635, "name": "ул. Братская, д. 27, к. 3"}, {"id": 7553675, "name": "ул. Владимирская 2-я, д. 45"}, {"id": 7553681, "name": "ул. Владимирская 2-я, д. 47, к. 1"}, {"id": 7554299, "name": "ул. Владимирская 2-я, д. 47, к. 2"}, {"id": 7554306, "name": "ул. Владимирская 2-я, д. 56"}, {"id": 7554310, "name": "ул. Владимирская 2-я, д. 57"}, {"id": 7554314, "name": "ул. Владимирская 2-я, д. 58"}, {"id": 7554321, "name": "ул. Владимирская 2-я, д. 59/39"}, {"id": 7555597, "name": "пр-кт. Зеленый, д. 22"}, {"id": 7915763, "name": "пр-кт. Зеленый, д. 26"}, {"id": 8930961, "name": "пр-кт. Зеленый, д. 30"}, {"id": 8930962, "name": "пр-кт. Зеленый, д. 32"}, {"id": 8954885, "name": "пр-кт. Зеленый, д. 32"}, {"id": 8930969, "name": "пр-кт. Зеленый, д. 34"}, {"id": 8954886, "name": "пр-кт. Зеленый, д. 34"}, {"id": 7555603, "name": "пр-кт. Зеленый, д. 40, к. 1"}, {"id": 7555607, "name": "пр-кт. Зеленый, д. 40, к. 2"}, {"id": 7555614, "name": "пр-кт. Зеленый, д. 42"}, {"id": 7555620, "name": "пр-кт. Зеленый, д. 44"}, {"id": 8930973, "name": "пр-кт. Зеленый, д. 46"}, {"id": 8954884, "name": "пр-кт. Зеленый, д. 46"}, {"id": 7555623, "name": "пр-кт. Зеленый, д. 48, к. 1"}, {"id": 7555630, "name": "пр-кт. Зеленый, д. 48, к. 2"}, {"id": 9067930, "name": "пр-кт. Зеленый, д. 48, к. 3"}, {"id": 7555636, "name": "пр-кт. Зеленый, д. 50"}, {"id": 7555640, "name": "пр-кт. Зеленый, д. 52, к. 1"}, {"id": 9067931, "name": "пр-кт. Зеленый, д. 52, к. 2"}, {"id": 7555646, "name": "пр-кт. Зеленый, д. 56"}, {"id": 7555653, "name": "пр-кт. Зеленый, д. 60/35"}, {"id": 8954887, "name": "пр-кт. Зеленый, д. 61"}, {"id": 8930975, "name": "пр-кт. Зеленый, д. 61"}, {"id": 7555657, "name": "пр-кт. Зеленый, д. 62, к. 1"}, {"id": 7555662, "name": "пр-кт. Зеленый, д. 62, к. 2"}, {"id": 7555670, "name": "пр-кт. Зеленый, д. 62, к. 3"}, {"id": 8125974, "name": "пр-кт. Зеленый, д. 63"}, {"id": 7555676, "name": "пр-кт. Зеленый, д. 64"}, {"id": 8930977, "name": "пр-кт. Зеленый, д. 65"}, {"id": 7555681, "name": "пр-кт. Зеленый, д. 66, к. 1"}, {"id": 7555686, "name": "пр-кт. Зеленый, д. 66, к. 2"}, {"id": 8945597, "name": "пр-кт. Зеленый, д. 67, к. 1"}, {"id": 8930979, "name": "пр-кт. Зеленый, д. 67, к. 1"}, {"id": 8930980, "name": "пр-кт. Зеленый, д. 67, к. 2"}, {"id": 7555695, "name": "пр-кт. Зеленый, д. 68, к. 1"}, {"id": 7555697, "name": "пр-кт. Зеленый, д. 68, к. 2"}, {"id": 8930983, "name": "пр-кт. Зеленый, д. 69, к. 1"}, {"id": 7555702, "name": "пр-кт. Зеленый, д. 69, к. 2"}, {"id": 7555713, "name": "пр-кт. Зеленый, д. 70, к. 1"}, {"id": 7555721, "name": "пр-кт. Зеленый, д. 70, к. 2"}, {"id": 8930985, "name": "пр-кт. Зеленый, д. 71, к. 1"}, {"id": 8954889, "name": "пр-кт. Зеленый, д. 71, к. 1"}, {"id": 7555725, "name": "пр-кт. Зеленый, д. 71, к. 2"}, {"id": 8950935, "name": "пр-кт. Зеленый, д. 73"}, {"id": 8930987, "name": "пр-кт. Зеленый, д. 73"}, {"id": 7555730, "name": "пр-кт. Зеленый, д. 74"}, {"id": 7555738, "name": "пр-кт. Зеленый, д. 76"}, {"id": 7555741, "name": "пр-кт. Зеленый, д. 77, к. 1"}, {"id": 7555750, "name": "пр-кт. Зеленый, д. 77, к. 2"}, {"id": 7555756, "name": "пр-кт. Зеленый, д. 83, к. 2"}, {"id": 7555761, "name": "пр-кт. Зеленый, д. 83, к. 3"}, {"id": 7555765, "name": "пр-кт. Зеленый, д. 83, к. 4"}, {"id": 7555770, "name": "пр-кт. Зеленый, д. 85"}, {"id": 7555774, "name": "пр-кт. Зеленый, д. 87, к. 1"}, {"id": 7555780, "name": "пр-кт. Зеленый, д. 87, к. 2"}, {"id": 7555785, "name": "ул. Коренная, д. 8, к. 1"}, {"id": 7555796, "name": "ул. Коренная, д. 8, к. 2"}, {"id": 7555802, "name": "ул. Коренная, д. 10"}, {"id": 7555859, "name": "ул. Кусковская, д. 16"}, {"id": 7555864, "name": "ул. Кусковская, д. 17"}, {"id": 7555872, "name": "ул. Кусковская, д. 17, к. 1"}, {"id": 7555879, "name": "ул. Кусковская, д. 19, к. 1"}, {"id": 7555882, "name": "ул. Кусковская, д. 19, к. 2"}, {"id": 7555890, "name": "ул. Кусковская, д. 21, к. 1"}, {"id": 7555897, "name": "ул. Кусковская, д. 21, к. 2"}, {"id": 7555900, "name": "ул. Кусковская, д. 21, к. 3"}, {"id": 7555906, "name": "ул. Кусковская, д. 23, к. 1"}, {"id": 7555909, "name": "ул. Кусковская, д. 23, к. 2"}, {"id": 7555913, "name": "ул. Кусковская, д. 23, к. 3"}, {"id": 7555915, "name": "ул. Кусковская, д. 23, к. 4"}, {"id": 7555920, "name": "ул. Кусковская, д. 23, к. 5"}, {"id": 7555932, "name": "ул. Кусковская, д. 25, к. 1"}, {"id": 7555936, "name": "ул. Кусковская, д. 25, к. 2"}, {"id": 7556260, "name": "ул. Кусковская, д. 27, к. 1"}, {"id": 7556262, "name": "ул. Кусковская, д. 27, к. 2"}, {"id": 7556265, "name": "ул. Кусковская, д. 29, к. 1"}, {"id": 7556268, "name": "ул. Кусковская, д. 29, к. 2"}, {"id": 7556270, "name": "ул. Кусковская, д. 31, к. 1"}, {"id": 7556273, "name": "ул. Кусковская, д. 31, к. 2"}, {"id": 7556274, "name": "ул. Кусковская, д. 33"}, {"id": 7556275, "name": "ул. Кусковская, д. 35, к. 1"}, {"id": 7556277, "name": "ул. Кусковская, д. 35, к. 2"}, {"id": 7556278, "name": "ул. Кусковская, д. 37/60"}, {"id": 7556279, "name": "ул. Кусковская, д. 41"}, {"id": 7556281, "name": "ул. Кусковская, д. 43, к. 1"}, {"id": 7556282, "name": "ул. Кусковская, д. 43, к. 2"}, {"id": 7556285, "name": "ул. Кусковская, д. 47"}, {"id": 8954891, "name": "ул. Мартеновская, д. 16/36"}, {"id": 8125978, "name": "ул. Мартеновская, д. 18"}, {"id": 7559466, "name": "ул. Мартеновская, д. 19"}, {"id": 8125981, "name": "ул. Мартеновская, д. 20"}, {"id": 8125985, "name": "ул. Мартеновская, д. 22, к. 1"}, {"id": 8125995, "name": "ул. Мартеновская, д. 22, к. 2"}, {"id": 8126000, "name": "ул. Мартеновская, д. 23"}, {"id": 7559471, "name": "ул. Мартеновская, д. 24"}, {"id": 7559474, "name": "ул. Мартеновская, д. 27"}, {"id": 8954892, "name": "ул. Мартеновская, д. 29"}, {"id": 8930993, "name": "ул. Мартеновская, д. 30"}, {"id": 7559487, "name": "ул. Мартеновская, д. 31"}, {"id": 8954893, "name": "ул. Мартеновская, д. 32/15"}, {"id": 7559493, "name": "ул. Мартеновская, д. 33"}, {"id": 7559499, "name": "ул. Мартеновская, д. 39, к. 1"}, {"id": 7559500, "name": "ул. Мартеновская, д. 39, к. 2"}, {"id": 7559504, "name": "ул. Мартеновская, д. 41"}, {"id": 9067912, "name": "ул. Металлургов, д. 62, к. 1"}, {"id": 7559534, "name": "проезд. Напольный, д. 6"}, {"id": 9067929, "name": "проезд. Напольный, д. 10"}, {"id": 8954896, "name": "ул. Новогиреевская, д. 37"}, {"id": 8954897, "name": "ул. Новогиреевская, д. 39"}, {"id": 7559539, "name": "ул. Новогиреевская, д. 41"}, {"id": 7559543, "name": "ул. Новогиреевская, д. 44/28"}, {"id": 8954898, "name": "ул. Новогиреевская, д. 45"}, {"id": 7559546, "name": "ул. Новогиреевская, д. 46"}, {"id": 8954901, "name": "ул. Новогиреевская, д. 47/26"}, {"id": 7559553, "name": "ул. Новогиреевская, д. 48"}, {"id": 8931008, "name": "ул. Новогиреевская, д. 49/28"}, {"id": 8954902, "name": "ул. Новогиреевская, д. 49/28"}, {"id": 7559556, "name": "ул. Новогиреевская, д. 50/9"}, {"id": 8954904, "name": "ул. Новогиреевская, д. 51, к. 1"}, {"id": 8126004, "name": "ул. Новогиреевская, д. 52"}, {"id": 8954906, "name": "ул. Новогиреевская, д. 53"}, {"id": 7559561, "name": "ул. Новогиреевская, д. 54"}, {"id": 7559721, "name": "ул. Перовская, д. 46, к. 1"}, {"id": 7559727, "name": "ул. Перовская, д. 46, к. 2"}, {"id": 7559731, "name": "ул. Перовская, д. 46, к. 3"}, {"id": 7559736, "name": "ул. Перовская, д. 46, к. 4"}, {"id": 7559740, "name": "ул. Перовская, д. 46, к. 5"}, {"id": 7559747, "name": "ул. Перовская, д. 48"}, {"id": 7559750, "name": "ул. Перовская, д. 49/53"}, {"id": 7559754, "name": "ул. Перовская, д. 50, к. 1"}, {"id": 7559756, "name": "ул. Перовская, д. 50, к. 4"}, {"id": 7559760, "name": "ул. Перовская, д. 50, к. 5"}, {"id": 7559763, "name": "ул. Перовская, д. 51"}, {"id": 7559767, "name": "ул. Перовская, д. 53"}, {"id": 7559768, "name": "ул. Перовская, д. 54/54"}, {"id": 7559771, "name": "ул. Перовская, д. 55"}, {"id": 7559773, "name": "ул. Перовская, д. 56/55"}, {"id": 7559775, "name": "ул. Перовская, д. 57"}, {"id": 7559776, "name": "ул. Перовская, д. 58"}, {"id": 7559778, "name": "ул. Перовская, д. 59"}, {"id": 7559824, "name": "ул. Перовская, д. 60, к. 1"}, {"id": 7559827, "name": "ул. Перовская, д. 60, к. 2"}, {"id": 7559834, "name": "ул. Перовская, д. 62"}, {"id": 8933011, "name": "ул. Перовская, д. 66, к. 1"}, {"id": 8933015, "name": "ул. Перовская, д. 66, к. 2"}, {"id": 8933018, "name": "ул. Перовская, д. 66, к. 3"}, {"id": 8933019, "name": "ул. Перовская, д. 66, к. 4"}, {"id": 8454309, "name": "ул. Перовская, д. 66, к. 5"}, {"id": 8302696, "name": "ул. Перовская, д. 66, к. 6"}, {"id": 8938882, "name": "ул. Перовская, д. 66, к. 7"}, {"id": 8942083, "name": "ул. Перовская, д. 66, к. 8"}, {"id": 8942086, "name": "ул. Перовская, д. 66, к. 9"}, {"id": 7559839, "name": "ул. Перовская, д. 73/43"}, {"id": 7559843, "name": "ул. Перовская, д. 75"}, {"id": 7559851, "name": "ул. Полимерная, д. 3"}, {"id": 7559856, "name": "ул. Полимерная, д. 5"}, {"id": 7559861, "name": "ул. Полимерная, д. 7"}, {"id": 7559864, "name": "проезд. Саперный, д. 2/23"}, {"id": 7559867, "name": "проезд. Саперный, д. 4"}, {"id": 7559871, "name": "проезд. Саперный, д. 6, к. 2"}, {"id": 7559874, "name": "проезд. Саперный, д. 8, к. 1"}, {"id": 7562160, "name": "проезд. Саперный, д. 8, к. 2"}, {"id": 7562161, "name": "проезд. Саперный, д. 8, к. 3"}, {"id": 7562162, "name": "проезд. Саперный, д. 9"}, {"id": 7562163, "name": "проезд. Саперный, д. 10"}, {"id": 7562164, "name": "проезд. Саперный, д. 11"}, {"id": 7562165, "name": "проезд. Саперный, д. 12, к. 1"}, {"id": 7562166, "name": "проезд. Саперный, д. 12, к. 2"}, {"id": 7562167, "name": "проезд. Саперный, д. 13"}, {"id": 7562168, "name": "пр-кт. Свободный, д. 6, к. 1"}, {"id": 7562169, "name": "пр-кт. Свободный, д. 6, к. 2"}, {"id": 7562170, "name": "пр-кт. Свободный, д. 6, к. 3"}, {"id": 7562171, "name": "пр-кт. Свободный, д. 10, к. 1"}, {"id": 7562172, "name": "пр-кт. Свободный, д. 10, к. 2"}, {"id": 7562173, "name": "пр-кт. Свободный, д. 12/23"}, {"id": 7562174, "name": "пр-кт. Свободный, д. 14"}, {"id": 7562175, "name": "пр-кт. Свободный, д. 16"}, {"id": 7562176, "name": "пр-кт. Свободный, д. 18"}, {"id": 7562177, "name": "пр-кт. Свободный, д. 20"}, {"id": 7562178, "name": "пр-кт. Свободный, д. 21/2"}, {"id": 7562179, "name": "пр-кт. Свободный, д. 22"}, {"id": 7562180, "name": "пр-кт. Свободный, д. 24"}, {"id": 7562181, "name": "пр-кт. Свободный, д. 25, к. 1"}, {"id": 7562182, "name": "пр-кт. Свободный, д. 25, к. 2"}, {"id": 7562183, "name": "пр-кт. Свободный, д. 26"}, {"id": 7563410, "name": "пр-кт. Свободный, д. 27"}, {"id": 7563411, "name": "пр-кт. Свободный, д. 28"}, {"id": 7563413, "name": "пр-кт. Свободный, д. 30"}, {"id": 7563414, "name": "пр-кт. Свободный, д. 32"}, {"id": 7346169, "name": "пр-кт. Свободный, д. 37, к. 2"}, {"id": 7563431, "name": "пр-кт. Свободный, д. 37/18"}, {"id": 7563434, "name": "пр-кт. Свободный, д. 39, к. 1"}, {"id": 7563436, "name": "пр-кт. Свободный, д. 39, к. 2"}, {"id": 8954907, "name": "пр-кт. Союзный, д. 4"}, {"id": 7563440, "name": "пр-кт. Союзный, д. 6, к. 1"}, {"id": 7563441, "name": "пр-кт. Союзный, д. 6, к. 2"}, {"id": 7563443, "name": "пр-кт. Союзный, д. 6, к. 3"}, {"id": 7563446, "name": "пр-кт. Союзный, д. 6, к. 4"}, {"id": 7563449, "name": "пр-кт. Союзный, д. 8, к. 1"}, {"id": 7563451, "name": "пр-кт. Союзный, д. 8, к. 2"}, {"id": 7563454, "name": "пр-кт. Союзный, д. 9, к. 1"}, {"id": 7563457, "name": "пр-кт. Союзный, д. 9, к. 2"}, {"id": 7563461, "name": "пр-кт. Союзный, д. 10"}, {"id": 7563463, "name": "пр-кт. Союзный, д. 12, к. 1"}, {"id": 7563466, "name": "пр-кт. Союзный, д. 12, к. 2"}, {"id": 8576450, "name": "пр-кт. Союзный, д. 13, к. 1"}, {"id": 7563476, "name": "пр-кт. Союзный, д. 13, к. 2"}, {"id": 7563478, "name": "пр-кт. Союзный, д. 14/9"}, {"id": 7563480, "name": "пр-кт. Союзный, д. 15, к. 1"}, {"id": 7563483, "name": "пр-кт. Союзный, д. 15, к. 2"}, {"id": 7563490, "name": "пр-кт. Союзный, д. 20, к. 1"}, {"id": 7563532, "name": "пр-кт. Союзный, д. 20, к. 2"}, {"id": 7563536, "name": "пр-кт. Союзный, д. 20, к. 3"}, {"id": 7563540, "name": "пр-кт. Союзный, д. 20, к. 4"}, {"id": 9067911, "name": "пр-кт. Союзный, д. 22"}, {"id": 9067927, "name": "пр-кт. Союзный, д. 22, к. 1"}, {"id": 9067928, "name": "пр-кт. Союзный, д. 22, к. 2"}, {"id": 7563549, "name": "пр-кт. Союзный, д. 24"}, {"id": 7563562, "name": "ул. Утренняя, д. 2/51"}, {"id": 7563563, "name": "ул. Утренняя, д. 3"}, {"id": 7563567, "name": "ул. Утренняя, д. 4"}, {"id": 7563568, "name": "ул. Утренняя, д. 6"}, {"id": 7563571, "name": "ул. Утренняя, д. 7"}, {"id": 7563572, "name": "ул. Утренняя, д. 8"}, {"id": 7563575, "name": "ул. Утренняя, д. 10, к. 1"}, {"id": 7563578, "name": "ул. Утренняя, д. 10, к. 2"}, {"id": 7563581, "name": "ул. Утренняя, д. 14, к. 1"}, {"id": 7563584, "name": "ул. Утренняя, д. 14, к. 2"}, {"id": 7563586, "name": "ул. Утренняя, д. 14, к. 3"}, {"id": 8126028, "name": "ул. Утренняя, д. 16, к. 1"}, {"id": 7563589, "name": "ул. Утренняя, д. 16, к. 2"}, {"id": 7563591, "name": "ул. Утренняя, д. 18, к. 1"}, {"id": 7563592, "name": "ул. Утренняя, д. 18, к. 2"}, {"id": 8126033, "name": "ул. Утренняя, д. 20"}, {"id": 7563593, "name": "ул. Утренняя, д. 22, к. 1"}, {"id": 7563595, "name": "ул. Утренняя, д. 22, к. 2"}, {"id": 8126045, "name": "пр-кт. Федеративный, д. 18, к. 1"}, {"id": 8126049, "name": "пр-кт. Федеративный, д. 18, к. 2"}, {"id": 8126060, "name": "пр-кт. Федеративный, д. 20"}, {"id": 7563601, "name": "пр-кт. Федеративный, д. 21, к. 1"}, {"id": 7563603, "name": "пр-кт. Федеративный, д. 21, к. 2"}, {"id": 7563605, "name": "пр-кт. Федеративный, д. 22, к. 1"}, {"id": 8126071, "name": "пр-кт. Федеративный, д. 22, к. 2"}, {"id": 8126075, "name": "пр-кт. Федеративный, д. 22, к. 3"}, {"id": 7563607, "name": "пр-кт. Федеративный, д. 24"}, {"id": 7563854, "name": "пр-кт. Федеративный, д. 24, к. 1"}, {"id": 8954908, "name": "пр-кт. Федеративный, д. 26, к. 4"}, {"id": 8931016, "name": "пр-кт. Федеративный, д. 26, к. 4"}, {"id": 7563857, "name": "пр-кт. Федеративный, д. 28"}, {"id": 7563860, "name": "пр-кт. Федеративный, д. 28А"}, {"id": 8931017, "name": "пр-кт. Федеративный, д. 30"}, {"id": 8945594, "name": "пр-кт. Федеративный, д. 30"}, {"id": 8931018, "name": "пр-кт. Федеративный, д. 30А, к. 1"}, {"id": 8950836, "name": "пр-кт. Федеративный, д. 30А, к. 1"}, {"id": 8950837, "name": "пр-кт. Федеративный, д. 30А, к. 2"}, {"id": 8931019, "name": "пр-кт. Федеративный, д. 30А, к. 2"}, {"id": 8954910, "name": "пр-кт. Федеративный, д. 32, к. 1"}, {"id": 8931020, "name": "пр-кт. Федеративный, д. 32, к. 1"}, {"id": 8931025, "name": "пр-кт. Федеративный, д. 32, к. 2"}, {"id": 8954912, "name": "пр-кт. Федеративный, д. 32, к. 2"}, {"id": 7563865, "name": "пр-кт. Федеративный, д. 33"}, {"id": 8931026, "name": "пр-кт. Федеративный, д. 34, к. 1"}, {"id": 8954913, "name": "пр-кт. Федеративный, д. 34, к. 1"}, {"id": 7563870, "name": "пр-кт. Федеративный, д. 34, к. 2"}, {"id": 7563874, "name": "пр-кт. Федеративный, д. 35"}, {"id": 8642709, "name": "пр-кт. Федеративный, д. 36"}, {"id": 7563879, "name": "пр-кт. Федеративный, д. 38, к. 1"}, {"id": 9069383, "name": "пр-кт. Федеративный, д. 38, к. 2"}, {"id": 7563884, "name": "пр-кт. Федеративный, д. 40, к. 1"}, {"id": 7563891, "name": "пр-кт. Федеративный, д. 40, к. 2"}, {"id": 7563897, "name": "пр-кт. Федеративный, д. 42, к. 1"}, {"id": 7563900, "name": "пр-кт. Федеративный, д. 42, к. 2"}, {"id": 7563907, "name": "пр-кт. Федеративный, д. 44"}, {"id": 7563910, "name": "пр-кт. Федеративный, д. 46, к. 1"}, {"id": 7563912, "name": "пр-кт. Федеративный, д. 46, к. 2"}, {"id": 7564382, "name": "ул. Фрязевская, д. 3, к. 1"}, {"id": 7564384, "name": "ул. Фрязевская, д. 3, к. 2"}, {"id": 7564385, "name": "ул. Фрязевская, д. 9, к. 1"}, {"id": 7564387, "name": "ул. Фрязевская, д. 9, к. 2"}, {"id": 7564401, "name": "ул. Фрязевская, д. 9, к. 3"}, {"id": 7564440, "name": "ул. Фрязевская, д. 11, к. 1"}, {"id": 9067922, "name": "ул. Фрязевская, д. 11, к. 2"}, {"id": 9067926, "name": "ул. Фрязевская, д. 11, к. 3"}, {"id": 7564441, "name": "ул. Фрязевская, д. 11, к. 4"}, {"id": 7564442, "name": "ул. Фрязевская, д. 11, к. 5"}, {"id": 7564443, "name": "ул. Фрязевская, д. 13"}, {"id": 7564444, "name": "ул. Фрязевская, д. 15, к. 1"}, {"id": 7564445, "name": "ул. Фрязевская, д. 15, к. 2"}, {"id": 7564446, "name": "ул. Фрязевская, д. 15, к. 3"}, {"id": 7564447, "name": "ул. Фрязевская, д. 15, к. 4"}, {"id": 7564448, "name": "ул. Фрязевская, д. 15, к. 5"}, {"id": 7564449, "name": "ул. Фрязевская, д. 15, к. 6"}]